[{"name":"2u","marks":69},{"name":"GR8eP6FbW","marks":91},{"name":"Ff6z","marks":39},{"name":"q1G","marks":13},{"name":"1k7djP","marks":14},{"name":"b7ny0","marks":4},{"name":"y","marks":92},{"name":"zeGDgRzWzn","marks":3},{"name":"kj8","marks":12},{"name":"KJ","marks":10},{"name":"SDdo","marks":84},{"name":"vz","marks":29},{"name":"ISvTfciW","marks":67},{"name":"0N","marks":95},{"name":"P54bLOtR4","marks":43},{"name":"n0qWW2exxq","marks":38},{"name":"LmNM","marks":39},{"name":"XKaIZ1","marks":18},{"name":"IObMlDIu","marks":86},{"name":"op","marks":79},{"name":"3Q58n5","marks":34},{"name":"trp2BKlrv","marks":21},{"name":"Hs","marks":11},{"name":"JwWMw9k5","marks":64},{"name":"8xOpeoOvE","marks":39},{"name":"FoTYYr2pj","marks":76},{"name":"On3","marks":9},{"name":"p","marks":22},{"name":"yLb9","marks":74},{"name":"eNxa8n3MsE","marks":78},{"name":"DW","marks":6},{"name":"l","marks":41},{"name":"Q4gxrBSw1","marks":1},{"name":"F1TQRPfol5","marks":29},{"name":"T5ztvtGTkC","marks":9},{"name":"5mmOBgx7","marks":13},{"name":"ARhAQtxR","marks":21},{"name":"bNCg","marks":97},{"name":"MZ","marks":57},{"name":"E6","marks":65},{"name":"I7Py","marks":43},{"name":"Qm","marks":63},{"name":"VwdZDIBYe","marks":3},{"name":"w0n","marks":40},{"name":"iE","marks":30},{"name":"ST","marks":38},{"name":"1ESo","marks":22},{"name":"9y1CXIb1ZI","marks":53},{"name":"8JY","marks":10},{"name":"usVRQs","marks":6},{"name":"g3cITRmJJ","marks":11},{"name":"GZddz","marks":28},{"name":"oy3l","marks":90},{"name":"I","marks":94},{"name":"KGQpZ1Io","marks":6},{"name":"sqRCaL","marks":21},{"name":"iBD","marks":79},{"name":"DsqNab","marks":83},{"name":"mdpP7nyxl","marks":33},{"name":"zDV","marks":97},{"name":"pOyp0gIVD9","marks":53},{"name":"BptG","marks":6},{"name":"W","marks":23},{"name":"m","marks":27},{"name":"Cg544f5gf","marks":7},{"name":"BeV6SCVu","marks":16},{"name":"O","marks":28},{"name":"Fg6NjlC","marks":39},{"name":"orOE9dMZ2J","marks":76},{"name":"3wE8Y7UH7","marks":23},{"name":"11","marks":29},{"name":"v37Y","marks":85},{"name":"t","marks":59},{"name":"pLfUH10BL","marks":13},{"name":"UfdMyRDYEF","marks":68},{"name":"YCznIlVu2","marks":5},{"name":"Rrmx8lw","marks":66},{"name":"cmtbdeVJ","marks":6},{"name":"udm1I","marks":20},{"name":"t1jP1bw","marks":40},{"name":"crg3","marks":32},{"name":"Q5","marks":59},{"name":"u","marks":20},{"name":"STC","marks":54},{"name":"q","marks":69},{"name":"rYQEtl","marks":37},{"name":"XFFHAH2Hz","marks":27},{"name":"IMPKeCKva","marks":61},{"name":"yrbcmkm72l","marks":80},{"name":"bVkg","marks":79},{"name":"4ty3A","marks":54},{"name":"4OP","marks":55},{"name":"F","marks":89},{"name":"cmGL7ONG","marks":14},{"name":"U1mge9x","marks":59},{"name":"V3h0DSfUE","marks":52},{"name":"YvG1S5Ra6","marks":80},{"name":"M6Gr8VJu","marks":41},{"name":"X","marks":6},{"name":"p","marks":38}]